ejercicio4/__init__.py
ejercicio4-1.0.dist-info/LICENSE
ejercicio4-1.0.dist-info/METADATA
ejercicio4-1.0.dist-info/WHEEL
ejercicio4-1.0.dist-info/top_level.txt
ejercicio4-1.0.dist-info/RECORD
