Metadata-Version: 2.1
Name: ejercicio4
Version: 1.0
Summary: A tool to find prime numbers between 0 and a number n.
Home-page: UNKNOWN
Author: Magalí Sierra
Author-email: maga_sierra@hotmail.com
License: GNU GPLv3
Keywords: prime number
Platform: UNKNOWN
Classifier: Development Status :: 4 - Beta
Classifier: Intended Audience :: Developers
Classifier: Topic :: Utilities
Classifier: License :: OSI Approved :: GNU General Public License v3 (GPLv3)
Classifier: Programming Language :: Python :: 3
Classifier: Operating System :: OS Independent
